kiwisolver/__init__.py
kiwisolver/_cext.cpython-312.so
kiwisolver/_cext.pyi
kiwisolver/exceptions.py
kiwisolver/py.typed
kiwisolver_qpython-1.4.7.dist-info/METADATA
kiwisolver_qpython-1.4.7.dist-info/WHEEL
kiwisolver_qpython-1.4.7.dist-info/top_level.txt
kiwisolver_qpython-1.4.7.dist-info/RECORD
